sap_ecs_log_forwarder/__init__.py
sap_ecs_log_forwarder/aws.py
sap_ecs_log_forwarder/azure.py
sap_ecs_log_forwarder/base_runner.py
sap_ecs_log_forwarder/cli.py
sap_ecs_log_forwarder/config.py
sap_ecs_log_forwarder/consumer.py
sap_ecs_log_forwarder/crypto.py
sap_ecs_log_forwarder/gcp.py
sap_ecs_log_forwarder/json_logging.py
sap_ecs_log_forwarder/metrics.py
sap_ecs_log_forwarder/processor.py
sap_ecs_log_forwarder/utils.py
sap_ecs_log_forwarder-1.0.0.dist-info/LICENSE
sap_ecs_log_forwarder-1.0.0.dist-info/METADATA
sap_ecs_log_forwarder-1.0.0.dist-info/WHEEL
sap_ecs_log_forwarder-1.0.0.dist-info/entry_points.txt
sap_ecs_log_forwarder-1.0.0.dist-info/RECORD
