Metadata-Version: 2.1
Name: sap-ecs-log-forwarder
Version: 1.0.0
Summary: A package to consume events from an AWS SQS queue, Azure Storage Account Topic and GCP PubSub Topic, process log files, and forward them to a HTTP endpoint or file.
Home-page: https://www.sap.com/
License: SAP DEVELOPER LICENSE AGREEMENT
Keywords: SAP AWS Log Forwarder,SAP Azure Log Forwarder,SAP GCP Log Forwarder,SAP Log Forwarder
Author: SAP SE
Requires-Python: >=3.10,<4.0
Classifier: Development Status :: 5 - Production/Stable
Classifier: Intended Audience :: Developers
Classifier: License :: Other/Proprietary License
Classifier: Operating System :: MacOS :: MacOS X
Classifier: Operating System :: POSIX :: Linux
Classifier: Programming Language :: Python :: 3
Classifier: Programming Language :: Python :: 3.10
Classifier: Programming Language :: Python :: 3.11
Classifier: Programming Language :: Python :: 3.12
Classifier: Programming Language :: Python :: 3.13
Classifier: Programming Language :: Python :: 3.14
Classifier: Topic :: Software Development :: Libraries :: Python Modules
Requires-Dist: aiohttp (>=3.13.2,<4.0.0)
Requires-Dist: azure-storage-blob (>=12.27.1,<13.0.0)
Requires-Dist: azure-storage-queue (>=12.14.1,<13.0.0)
Requires-Dist: boto3 (>=1.17.49,<2.0.0)
Requires-Dist: click (>=8.3.0,<9.0.0)
Requires-Dist: cryptography (>=44.0.1,<45.0.0)
Requires-Dist: google-cloud-pubsub (>=2.33.0,<3.0.0)
Requires-Dist: google-cloud-storage (>=3.6.0,<4.0.0)
Requires-Dist: requests (>=2.32.4,<3.0.0)
Requires-Dist: urllib3 (>=2.5.0,<3.0.0)
